{
  "topic": "NAARAH",
  "topic_slug": "naarah",
  "canonical_id": "NAV:naarah",
  "aliases": [],
  "see_also": [],
  "see_also_resolved": [],
  "raw_block": "–A wife of Ashur1Ch 4:5,6",
  "content_preview": "–A wife of Ashur1Ch 4:5,6",
  "reference_groups": [
    {
      "idx": 0,
      "entry_label": "–A wife of Ashur1Ch 4:5,6",
      "raw_segment": "–A wife of Ashur1Ch 4:5,6"
    }
  ],
  "biblical_references": [],
  "books_mentioned": [],
  "normalized_labels": [],
  "stats": {
    "entries_count": 1,
    "ot_refs": 0,
    "nt_refs": 0,
    "total_verses": 0,
    "top_books": [],
    "ref_counts_by_book": {}
  },
  "source": {
    "provider": "ccel",
    "work": "Nave's Topical Bible",
    "format": "xml",
    "fetched_at": "2025-09-20",
    "source_url": null,
    "local_file": "data/datasets/ccel-paragraphs/ccel/n/nave/bible.xml"
  },
  "metadata": {
    "parser": "ccel-nave-xml-parser",
    "parser_version": "2025.09.19",
    "schema_version": "scrape.v1",
    "language": {
      "code": "en",
      "name": "English",
      "direction": "ltr"
    },
    "integrity": {
      "checksum_raw_block": "sha256:c16f17fdea66650b270a3cf9c48f9f091884817d58b5d7ff4d603d0608c962de",
      "position": {
        "start_line": null,
        "end_line": null,
        "total_lines": 1
      }
    },
    "notes": [
      "XML-based parsing from official CCEL ThML source",
      "Perfect biblical reference extraction with osisRef",
      "Structured hierarchy preservation",
      "Complete topic linking and see_also resolution"
    ]
  },
  "total_references": 0,
  "version": "1.0.0",
  "created_at": "2025-09-20T17:29:22.631353Z",
  "updated_at": "2025-09-20T17:29:22.631360Z"
}