{
  "topic": "SENSUALITY",
  "topic_slug": "sensuality",
  "canonical_id": "NAV:sensuality",
  "aliases": [],
  "see_also": [
    "SODOMY",
    "SELF-DENIAL",
    "DRUNKENNESS",
    "SELF-INDULGENCE",
    "FORNICATION",
    "LASCIVIOUSNESS",
    "ABSTINENCE, TOTAL",
    "CONTINENCE",
    "ADULTERY",
    "TEMPERANCE",
    "GLUTTONY"
  ],
  "see_also_resolved": [
    {
      "original": "SODOMY",
      "clean": "SODOMY",
      "slug": "sodomy",
      "canonical_id": "NAV:sodomy"
    },
    {
      "original": "SELF-DENIAL",
      "clean": "SELF-DENIAL",
      "slug": "self_denial",
      "canonical_id": "NAV:self_denial"
    },
    {
      "original": "DRUNKENNESS",
      "clean": "DRUNKENNESS",
      "slug": "drunkenness",
      "canonical_id": "NAV:drunkenness"
    },
    {
      "original": "SELF-INDULGENCE",
      "clean": "SELF-INDULGENCE",
      "slug": "self_indulgence",
      "canonical_id": "NAV:self_indulgence"
    },
    {
      "original": "FORNICATION",
      "clean": "FORNICATION",
      "slug": "fornication",
      "canonical_id": "NAV:fornication"
    },
    {
      "original": "LASCIVIOUSNESS",
      "clean": "LASCIVIOUSNESS",
      "slug": "lasciviousness",
      "canonical_id": "NAV:lasciviousness"
    },
    {
      "original": "ABSTINENCE, TOTAL",
      "clean": "ABSTINENCE, TOTAL",
      "slug": "abstinence__total",
      "canonical_id": "NAV:abstinence__total"
    },
    {
      "original": "CONTINENCE",
      "clean": "CONTINENCE",
      "slug": "continence",
      "canonical_id": "NAV:continence"
    },
    {
      "original": "ADULTERY",
      "clean": "ADULTERY",
      "slug": "adultery",
      "canonical_id": "NAV:adultery"
    },
    {
      "original": "TEMPERANCE",
      "clean": "TEMPERANCE",
      "slug": "temperance",
      "canonical_id": "NAV:temperance"
    },
    {
      "original": "GLUTTONY",
      "clean": "GLUTTONY",
      "slug": "gluttony",
      "canonical_id": "NAV:gluttony"
    }
  ],
  "raw_block": "–General scriptures concerningEc 2:24;8:15;11:9;Isa 22:13;56:12;Lu 12:19,20;16:25;1Co 15:32,33;Jas 5:5;Jude 1:18,19\n–SeeADULTERY\n–SeeDRUNKENNESS\n–SeeFORNICATION\n–SeeGLUTTONY\n–SeeLASCIVIOUSNESS\n–SeeSELF-INDULGENCE\n–SeeSODOMY\n–Also seeABSTINENCE, TOTAL\n–SeeCONTINENCE\n–SeeSELF-DENIAL\n–SeeTEMPERANCE",
  "content_preview": "–General scriptures concerningEc 2:24;8:15;11:9;Isa 22:13;56:12;Lu 12:19,20;16:25;1Co 15:32,33;Jas 5...",
  "reference_groups": [
    {
      "idx": 0,
      "entry_label": "–General scriptures concerningEc 2:24;8:15;11:9;Isa 22:13;56:12;Lu 12:19,20;16:25;1Co 15:32,33;Jas 5:5;Jude 1:18,19",
      "raw_segment": "–General scriptures concerningEc 2:24;8:15;11:9;Isa 22:13;56:12;Lu 12:19,20;16:25;1Co 15:32,33;Jas 5:5;Jude 1:18,19"
    },
    {
      "idx": 1,
      "entry_label": "–SeeADULTERY",
      "raw_segment": "–SeeADULTERY"
    },
    {
      "idx": 2,
      "entry_label": "–SeeDRUNKENNESS",
      "raw_segment": "–SeeDRUNKENNESS"
    },
    {
      "idx": 3,
      "entry_label": "–SeeFORNICATION",
      "raw_segment": "–SeeFORNICATION"
    },
    {
      "idx": 4,
      "entry_label": "–SeeGLUTTONY",
      "raw_segment": "–SeeGLUTTONY"
    },
    {
      "idx": 5,
      "entry_label": "–SeeLASCIVIOUSNESS",
      "raw_segment": "–SeeLASCIVIOUSNESS"
    },
    {
      "idx": 6,
      "entry_label": "–SeeSELF-INDULGENCE",
      "raw_segment": "–SeeSELF-INDULGENCE"
    },
    {
      "idx": 7,
      "entry_label": "–SeeSODOMY",
      "raw_segment": "–SeeSODOMY"
    },
    {
      "idx": 8,
      "entry_label": "–Also seeABSTINENCE, TOTAL",
      "raw_segment": "–Also seeABSTINENCE, TOTAL"
    },
    {
      "idx": 9,
      "entry_label": "–SeeCONTINENCE",
      "raw_segment": "–SeeCONTINENCE"
    },
    {
      "idx": 10,
      "entry_label": "–SeeSELF-DENIAL",
      "raw_segment": "–SeeSELF-DENIAL"
    },
    {
      "idx": 11,
      "entry_label": "–SeeTEMPERANCE",
      "raw_segment": "–SeeTEMPERANCE"
    }
  ],
  "biblical_references": [],
  "books_mentioned": [],
  "normalized_labels": [],
  "stats": {
    "entries_count": 1,
    "ot_refs": 0,
    "nt_refs": 0,
    "total_verses": 0,
    "top_books": [],
    "ref_counts_by_book": {}
  },
  "source": {
    "provider": "ccel",
    "work": "Nave's Topical Bible",
    "format": "xml",
    "fetched_at": "2025-09-20",
    "source_url": null,
    "local_file": "data/datasets/ccel-paragraphs/ccel/n/nave/bible.xml"
  },
  "metadata": {
    "parser": "ccel-nave-xml-parser",
    "parser_version": "2025.09.19",
    "schema_version": "scrape.v1",
    "language": {
      "code": "en",
      "name": "English",
      "direction": "ltr"
    },
    "integrity": {
      "checksum_raw_block": "sha256:3b559abcb7d5a1e9ebde657d3cddb31c60950b48797c0eb58fcf7262069ecf3f",
      "position": {
        "start_line": null,
        "end_line": null,
        "total_lines": 12
      }
    },
    "notes": [
      "XML-based parsing from official CCEL ThML source",
      "Perfect biblical reference extraction with osisRef",
      "Structured hierarchy preservation",
      "Complete topic linking and see_also resolution"
    ]
  },
  "total_references": 0,
  "version": "1.0.0",
  "created_at": "2025-09-20T17:31:03.615601Z",
  "updated_at": "2025-09-20T17:31:03.615612Z"
}