{
  "topic": "John, The Second And Third Epistles Of",
  "slug": "john-the-second-and-third-epistles-of",
  "type": "dictionary",
  "reference_groups": [],
  "biblical_references": [],
  "stats": {},
  "definitions": [
    {
      "source": "SMI",
      "text": "The second epistle is addressed to an individual woman. One who had children, and a sister and nieces, is clearly indicated. According to one interpretation she is “the Lady Electa,” to another, “the elect Kyria,” to a third, “the elect Lady.” The third epistle is addressed to Caius or Gaius. He was probably a convert of St. John, Epist. (3 John 1:4) and a layman of wealth and distinction, Epits. (3 John 1:5) in some city near Ephesus. The object of St. John in writing the second epistle was to warn the lady to whom he wrote against abetting the teaching known as that of Basilides and his followers, by perhaps an undue kindness displayed by her toward the preachers of the false doctrine. The third epistle was written for the purpose of commending to the kindness and hospitality of Caius some Christians who were strangers in the place where he lived. It is probably that these Christians carried this letter with them to Caius as their introduction.",
      "extracted_refs": [
        {
          "book": "3 John",
          "chapter": 1,
          "verses": [
            4
          ],
          "verse_count": 1,
          "testament": "NT",
          "raw": "3 John 1:4",
          "source": "SMI"
        },
        {
          "book": "3 John",
          "chapter": 1,
          "verses": [
            5
          ],
          "verse_count": 1,
          "testament": "NT",
          "raw": "3 John 1:5",
          "source": "SMI"
        }
      ]
    }
  ],
  "dictionary_refs": [
    {
      "reference": "3 John 1:1",
      "original": "3 John 1"
    }
  ],
  "sources": [
    "SMI"
  ],
  "metadata": {
    "schema_version": "v3.0",
    "created_at": "2025-12-02T21:53:08.697435+00:00",
    "merged_from": {
      "v2": false,
      "dictionary": true
    }
  },
  "version": "3.0.0",
  "definition_refs": [
    {
      "book": "3 John",
      "chapter": 1,
      "verses": [
        4
      ],
      "verse_count": 1,
      "testament": "NT",
      "raw": "3 John 1:4",
      "source": "SMI"
    },
    {
      "book": "3 John",
      "chapter": 1,
      "verses": [
        5
      ],
      "verse_count": 1,
      "testament": "NT",
      "raw": "3 John 1:5",
      "source": "SMI"
    }
  ],
  "definition_refs_stats": {
    "total": 2,
    "ot": 0,
    "nt": 2,
    "books": [
      "3 John"
    ]
  }
}