{
  "topic": "Beg",
  "slug": "beg",
  "type": "dictionary",
  "reference_groups": [],
  "biblical_references": [],
  "stats": {},
  "definitions": [
    {
      "source": "EAS",
      "text": "That the poor existed among the Hebrews we have abundant evidence (Ex. 23:11; Deut. 15:11), but there is no mention of beggars properly so called in the Old Testament. The poor were provided for by the law of Moses (Lev. 19:10; Deut. 12:12; 14:29). It is predicted of the seed of the wicked that they shall be beggars (Ps. 37:25; 109:10). In the New Testament we find not seldom mention made of beggars (Mark 10:46; Luke 16:20, 21; Acts 3:2), yet there is no mention of such a class as vagrant beggars, so numerous in the East. “Beggarly,” in Gal. 4:9, means worthless.",
      "extracted_refs": [
        {
          "book": "Exodus",
          "chapter": 23,
          "verses": [
            11
          ],
          "verse_count": 1,
          "testament": "OT",
          "raw": "Exodus 23:11",
          "source": "EAS"
        },
        {
          "book": "Deuteronomy",
          "chapter": 15,
          "verses": [
            11
          ],
          "verse_count": 1,
          "testament": "OT",
          "raw": "Deuteronomy 15:11",
          "source": "EAS"
        },
        {
          "book": "Leviticus",
          "chapter": 19,
          "verses": [
            10
          ],
          "verse_count": 1,
          "testament": "OT",
          "raw": "Leviticus 19:10",
          "source": "EAS"
        },
        {
          "book": "Deuteronomy",
          "chapter": 12,
          "verses": [
            12
          ],
          "verse_count": 1,
          "testament": "OT",
          "raw": "Deuteronomy 12:12",
          "source": "EAS"
        },
        {
          "book": "Deuteronomy",
          "chapter": 14,
          "verses": [
            29
          ],
          "verse_count": 1,
          "testament": "OT",
          "raw": "Deuteronomy 14:29",
          "source": "EAS"
        },
        {
          "book": "Psalms",
          "chapter": 37,
          "verses": [
            25
          ],
          "verse_count": 1,
          "testament": "OT",
          "raw": "Psalms 37:25",
          "source": "EAS"
        },
        {
          "book": "Psalms",
          "chapter": 109,
          "verses": [
            10
          ],
          "verse_count": 1,
          "testament": "OT",
          "raw": "Psalms 109:10",
          "source": "EAS"
        },
        {
          "book": "Mark",
          "chapter": 10,
          "verses": [
            46
          ],
          "verse_count": 1,
          "testament": "NT",
          "raw": "Mark 10:46",
          "source": "EAS"
        },
        {
          "book": "Luke",
          "chapter": 16,
          "verses": [
            20,
            21
          ],
          "verse_count": 2,
          "testament": "NT",
          "raw": "Luke 16:20, 21",
          "source": "EAS"
        },
        {
          "book": "Acts",
          "chapter": 3,
          "verses": [
            2
          ],
          "verse_count": 1,
          "testament": "NT",
          "raw": "Acts 3:2",
          "source": "EAS"
        },
        {
          "book": "Galatians",
          "chapter": 4,
          "verses": [
            9
          ],
          "verse_count": 1,
          "testament": "NT",
          "raw": "Galatians 4:9",
          "source": "EAS"
        }
      ]
    }
  ],
  "dictionary_refs": [
    {
      "reference": "Exodus 23:11",
      "original": "Ex. 23:11"
    },
    {
      "reference": "Deuteronomy 15:11",
      "original": "Deut. 15:11"
    },
    {
      "reference": "Leviticus 19:10",
      "original": "Lev. 19:10"
    },
    {
      "reference": "Deuteronomy 12:12",
      "original": "Deut. 12:12"
    },
    {
      "reference": "Deuteronomy 14:29",
      "original": "Deut 14:29"
    },
    {
      "reference": "Psalms 37:25",
      "original": "Ps. 37:25"
    },
    {
      "reference": "Psalms 109:10",
      "original": "Ps 109:10"
    },
    {
      "reference": "Mark 10:46",
      "original": "Mark 10:46"
    },
    {
      "reference": "Luke 16:20",
      "original": "Luke 16:20"
    },
    {
      "reference": "Luke 16:21",
      "original": "Luke 16:21"
    },
    {
      "reference": "Acts 3:2",
      "original": "Acts 3:2"
    },
    {
      "reference": "Galatians 4:9",
      "original": "Gal. 4:9"
    }
  ],
  "sources": [
    "EAS"
  ],
  "metadata": {
    "schema_version": "v3.0",
    "created_at": "2025-12-02T21:53:08.672927+00:00",
    "merged_from": {
      "v2": false,
      "dictionary": true
    }
  },
  "version": "3.0.0",
  "definition_refs": [
    {
      "book": "Exodus",
      "chapter": 23,
      "verses": [
        11
      ],
      "verse_count": 1,
      "testament": "OT",
      "raw": "Exodus 23:11",
      "source": "EAS"
    },
    {
      "book": "Deuteronomy",
      "chapter": 15,
      "verses": [
        11
      ],
      "verse_count": 1,
      "testament": "OT",
      "raw": "Deuteronomy 15:11",
      "source": "EAS"
    },
    {
      "book": "Leviticus",
      "chapter": 19,
      "verses": [
        10
      ],
      "verse_count": 1,
      "testament": "OT",
      "raw": "Leviticus 19:10",
      "source": "EAS"
    },
    {
      "book": "Deuteronomy",
      "chapter": 12,
      "verses": [
        12
      ],
      "verse_count": 1,
      "testament": "OT",
      "raw": "Deuteronomy 12:12",
      "source": "EAS"
    },
    {
      "book": "Deuteronomy",
      "chapter": 14,
      "verses": [
        29
      ],
      "verse_count": 1,
      "testament": "OT",
      "raw": "Deuteronomy 14:29",
      "source": "EAS"
    },
    {
      "book": "Psalms",
      "chapter": 37,
      "verses": [
        25
      ],
      "verse_count": 1,
      "testament": "OT",
      "raw": "Psalms 37:25",
      "source": "EAS"
    },
    {
      "book": "Psalms",
      "chapter": 109,
      "verses": [
        10
      ],
      "verse_count": 1,
      "testament": "OT",
      "raw": "Psalms 109:10",
      "source": "EAS"
    },
    {
      "book": "Mark",
      "chapter": 10,
      "verses": [
        46
      ],
      "verse_count": 1,
      "testament": "NT",
      "raw": "Mark 10:46",
      "source": "EAS"
    },
    {
      "book": "Luke",
      "chapter": 16,
      "verses": [
        20,
        21
      ],
      "verse_count": 2,
      "testament": "NT",
      "raw": "Luke 16:20, 21",
      "source": "EAS"
    },
    {
      "book": "Acts",
      "chapter": 3,
      "verses": [
        2
      ],
      "verse_count": 1,
      "testament": "NT",
      "raw": "Acts 3:2",
      "source": "EAS"
    },
    {
      "book": "Galatians",
      "chapter": 4,
      "verses": [
        9
      ],
      "verse_count": 1,
      "testament": "NT",
      "raw": "Galatians 4:9",
      "source": "EAS"
    }
  ],
  "definition_refs_stats": {
    "total": 12,
    "ot": 7,
    "nt": 5,
    "books": [
      "Acts",
      "Deuteronomy",
      "Exodus",
      "Galatians",
      "Leviticus",
      "Luke",
      "Mark",
      "Psalms"
    ]
  }
}