{
  "topic": "SINCERITY",
  "slug": "sincerity",
  "type": "topic",
  "reference_groups": [
    {
      "name": "Does not exempt from guilt Ge 20",
      "references": [
        "Gen 20"
      ],
      "sub_groups": []
    },
    {
      "name": "See IGNORANCE, SINS OF",
      "references": [],
      "sub_groups": []
    },
    {
      "name": "Forgiveness of enemies must be sincere Mt 18:35",
      "references": [
        "Matt 18:35"
      ],
      "sub_groups": []
    },
    {
      "name": "Servants must render honest service Eph 6:5-7",
      "references": [
        "Eph 6:5-7"
      ],
      "sub_groups": []
    },
    {
      "name": "Whatever is done must be done with 1Co 10:31",
      "references": [
        "1Cor 10:31"
      ],
      "sub_groups": []
    },
    {
      "name": "Jesus was an example of 1Pe 2:22",
      "references": [
        "1Pet 2:22"
      ],
      "sub_groups": []
    },
    {
      "name": "Servants of should be examples of Tit 2:7",
      "references": [
        "Titus 2:7"
      ],
      "sub_groups": []
    },
    {
      "name": "Opposed to fleshly wisdom 2Co 1:12",
      "references": [
        "2Cor 1:12"
      ],
      "sub_groups": []
    },
    {
      "name": "Should characterize",
      "references": [],
      "sub_groups": [
        {
          "name": "Our love toward God 2Co 8:8,24",
          "references": [
            "2Cor 8:8",
            "2Cor 8:24"
          ]
        },
        {
          "name": "Our love toward Jesus Eph 6:24",
          "references": [
            "Eph 6:24"
          ]
        },
        {
          "name": "Our service toward God Jos 24:14",
          "references": [
            "Josh 24:14"
          ]
        },
        {
          "name": "Our faith 1Ti 1:5",
          "references": [
            "1Tim 1:5"
          ]
        },
        {
          "name": "Our love to one another Ro 12:9; 1Pe 1:22; 1Jo 3:18",
          "references": [
            "Rom 12:9",
            "1Pet 1:22",
            "1John 3:18"
          ]
        },
        {
          "name": "Our whole conduct 2Co 1:12",
          "references": [
            "2Cor 1:12"
          ]
        },
        {
          "name": "The preaching of the gospel 2Co 2:17; 1Th 2:3-5",
          "references": [
            "2Cor 2:17",
            "1Thess 2:3-5"
          ]
        }
      ]
    },
    {
      "name": "A characteristic of the doctrines of the gospel 1Pe 2:2",
      "references": [
        "1Pet 2:2"
      ],
      "sub_groups": []
    },
    {
      "name": "The gospel sometimes preached without Php 1:16",
      "references": [
        "Phil 1:16"
      ],
      "sub_groups": []
    },
    {
      "name": "Evil people are devoid of Ps 5:9; 55:21",
      "references": [
        "Ps 5:9",
        "Ps 55:21"
      ],
      "sub_groups": []
    },
    {
      "name": "Exhortations to 1Co 5:8; 1Pe 2:1",
      "references": [
        "1Cor 5:8",
        "1Pet 2:1"
      ],
      "sub_groups": []
    },
    {
      "name": "Prayer for, on behalf of others Php 1:10",
      "references": [
        "Phil 1:10"
      ],
      "sub_groups": []
    },
    {
      "name": "Blessedness of Ps 32:2",
      "references": [
        "Ps 32:2"
      ],
      "sub_groups": []
    },
    {
      "name": "EXEMPLIFIED",
      "references": [],
      "sub_groups": [
        {
          "name": "By some men of the tribe of Zebulun 1Ch 12:33",
          "references": [
            "1Chr 12:33"
          ]
        },
        {
          "name": "By Hezekiah Isa 38:3",
          "references": [
            "Isa 38:3"
          ]
        },
        {
          "name": "By Nathanael Joh 1:47",
          "references": [
            "John 1:47"
          ]
        },
        {
          "name": "By Paul 2Co 1:12",
          "references": [
            "2Cor 1:12"
          ]
        },
        {
          "name": "By Timothy 2Ti 1:5",
          "references": [
            "2Tim 1:5"
          ]
        },
        {
          "name": "By Lois and Eunice 2Ti 1:5",
          "references": [
            "2Tim 1:5"
          ]
        }
      ]
    }
  ],
  "biblical_references": [
    {
      "book": "1 Pet",
      "book_abbrev": "1 p",
      "chapter": 2,
      "testament": "NT",
      "verses": [
        22
      ],
      "verse_count": 1
    },
    {
      "book": "Titus",
      "book_abbrev": "tit",
      "chapter": 2,
      "testament": "NT",
      "verses": [
        7
      ],
      "verse_count": 1
    },
    {
      "book": "2 Cor",
      "book_abbrev": "2 c",
      "chapter": 1,
      "testament": "NT",
      "verses": [
        12
      ],
      "verse_count": 1
    },
    {
      "book": "2 Cor",
      "book_abbrev": "2 c",
      "chapter": 8,
      "testament": "NT",
      "verses": [
        8
      ],
      "verse_count": 1
    },
    {
      "book": "2 Cor",
      "book_abbrev": "2 c",
      "chapter": 8,
      "testament": "NT",
      "verses": [
        24
      ],
      "verse_count": 1
    },
    {
      "book": "Eph",
      "book_abbrev": "eph",
      "chapter": 6,
      "testament": "NT",
      "verses": [
        24
      ],
      "verse_count": 1
    },
    {
      "book": "Josh",
      "book_abbrev": "jos",
      "chapter": 24,
      "testament": "OT",
      "verses": [
        14
      ],
      "verse_count": 1
    },
    {
      "book": "John",
      "book_abbrev": "jhn",
      "chapter": 4,
      "testament": "NT",
      "verses": [
        23
      ],
      "verse_count": 1
    },
    {
      "book": "John",
      "book_abbrev": "jhn",
      "chapter": 4,
      "testament": "NT",
      "verses": [
        24
      ],
      "verse_count": 1
    },
    {
      "book": "1 Tim",
      "book_abbrev": "1 t",
      "chapter": 1,
      "testament": "NT",
      "verses": [
        5
      ],
      "verse_count": 1
    },
    {
      "book": "Rom",
      "book_abbrev": "rom",
      "chapter": 12,
      "testament": "NT",
      "verses": [
        9
      ],
      "verse_count": 1
    },
    {
      "book": "1 Pet",
      "book_abbrev": "1 p",
      "chapter": 1,
      "testament": "NT",
      "verses": [
        22
      ],
      "verse_count": 1
    },
    {
      "book": "1 John",
      "book_abbrev": "1jn",
      "chapter": 3,
      "testament": "NT",
      "verses": [
        18
      ],
      "verse_count": 1
    },
    {
      "book": "2 Cor",
      "book_abbrev": "2 c",
      "chapter": 2,
      "testament": "NT",
      "verses": [
        17
      ],
      "verse_count": 1
    },
    {
      "book": "1 Thess",
      "book_abbrev": "1 t",
      "chapter": 2,
      "testament": "NT",
      "verses": [
        3,
        4,
        5
      ],
      "verse_count": 3
    },
    {
      "book": "1 Pet",
      "book_abbrev": "1 p",
      "chapter": 2,
      "testament": "NT",
      "verses": [
        2
      ],
      "verse_count": 1
    },
    {
      "book": "Phil",
      "book_abbrev": "phi",
      "chapter": 1,
      "testament": "NT",
      "verses": [
        16
      ],
      "verse_count": 1
    },
    {
      "book": "Ps",
      "book_abbrev": "ps",
      "chapter": 5,
      "testament": "OT",
      "verses": [
        9
      ],
      "verse_count": 1
    },
    {
      "book": "Ps",
      "book_abbrev": "ps",
      "chapter": 55,
      "testament": "OT",
      "verses": [
        21
      ],
      "verse_count": 1
    },
    {
      "book": "Ps",
      "book_abbrev": "ps",
      "chapter": 34,
      "testament": "OT",
      "verses": [
        13
      ],
      "verse_count": 1
    },
    {
      "book": "1 Cor",
      "book_abbrev": "1 c",
      "chapter": 5,
      "testament": "NT",
      "verses": [
        8
      ],
      "verse_count": 1
    },
    {
      "book": "1 Pet",
      "book_abbrev": "1 p",
      "chapter": 2,
      "testament": "NT",
      "verses": [
        1
      ],
      "verse_count": 1
    },
    {
      "book": "Phil",
      "book_abbrev": "phi",
      "chapter": 1,
      "testament": "NT",
      "verses": [
        10
      ],
      "verse_count": 1
    },
    {
      "book": "Ps",
      "book_abbrev": "ps",
      "chapter": 32,
      "testament": "OT",
      "verses": [
        2
      ],
      "verse_count": 1
    },
    {
      "book": "1 Chr",
      "book_abbrev": "1 c",
      "chapter": 12,
      "testament": "OT",
      "verses": [
        33
      ],
      "verse_count": 1
    },
    {
      "book": "Isa",
      "book_abbrev": "isa",
      "chapter": 38,
      "testament": "OT",
      "verses": [
        3
      ],
      "verse_count": 1
    },
    {
      "book": "John",
      "book_abbrev": "jhn",
      "chapter": 1,
      "testament": "NT",
      "verses": [
        47
      ],
      "verse_count": 1
    },
    {
      "book": "2 Tim",
      "book_abbrev": "2 t",
      "chapter": 1,
      "testament": "NT",
      "verses": [
        5
      ],
      "verse_count": 1
    },
    {
      "book": "Rev",
      "book_abbrev": "rev",
      "chapter": 14,
      "testament": "NT",
      "verses": [
        5
      ],
      "verse_count": 1
    },
    {
      "book": "1 Thessalonians",
      "book_abbrev": "1th",
      "chapter": 2,
      "testament": "NT",
      "verses": [
        3,
        4,
        5
      ],
      "verse_count": 3
    },
    {
      "book": "1 Peter",
      "book_abbrev": "1pe",
      "chapter": 1,
      "testament": "NT",
      "verses": [
        1,
        22
      ],
      "verse_count": 2
    },
    {
      "book": "1 Peter",
      "book_abbrev": "1pe",
      "chapter": 2,
      "testament": "NT",
      "verses": [
        1
      ],
      "verse_count": 1
    }
  ],
  "see_also": [
    "IGNORANCE, SINS OF"
  ],
  "aliases": [],
  "stats": {
    "total_aspects": 25,
    "level1_aspects": 11,
    "level2_aspects": 14,
    "total_refs": 32,
    "ot_refs": 7,
    "nt_refs": 25
  },
  "sources": [
    "NAV",
    "TOR"
  ],
  "metadata": {
    "schema_version": "v3.0",
    "created_at": "2025-12-02T21:53:08.726583+00:00",
    "merged_from": {
      "v2": true,
      "dictionary": false
    }
  },
  "version": "3.0.0"
}