{
  "topic": "STUMBLING",
  "slug": "stumbling",
  "type": "topic",
  "reference_groups": [
    {
      "name": "FIGURATIVE",
      "references": [],
      "sub_groups": [
        {
          "name": "Causes of Ps 69:6",
          "references": [
            "Ps 69:6"
          ]
        },
        {
          "name": "Stone of Isa 8:14; Ro 9:32,33; 1Pe 1:8",
          "references": [
            "Isa 8:14",
            "Rom 9:32",
            "Rom 9:33",
            "1Pet 1:8"
          ]
        },
        {
          "name": "Stumbling-block Le 19:14; Ps 119:165",
          "references": [
            "Lev 19:14",
            "Ps 119:165"
          ]
        },
        {
          "name": "R. V.) Isa 57:14; Jer 6:21; Eze 3:20; 7:19; 14:3,4,7; Zep 1:3; Lu 11:52; Ro 11:9; 14:13; 1Co 1:23; 8:9-13; Re 2:14",
          "references": [
            "Isa 57:14",
            "Jer 6:21",
            "Ezek 3:20",
            "Ezek 7:19",
            "Ezek 14:3",
            "Ezek 14:4",
            "Ezek 14:7",
            "Zeph 1:3",
            "Luke 11:52",
            "Rom 11:9",
            "Rom 14:13",
            "1Cor 1:23",
            "1Cor 8:9-13",
            "Rev 2:14"
          ]
        }
      ]
    }
  ],
  "biblical_references": [
    {
      "book": "Psalms",
      "book_abbrev": "psa",
      "chapter": 119,
      "testament": "OT",
      "verses": [
        165
      ],
      "verse_count": 1
    },
    {
      "book": "Isaiah",
      "book_abbrev": "isa",
      "chapter": 57,
      "testament": "OT",
      "verses": [
        14
      ],
      "verse_count": 1
    },
    {
      "book": "Jeremiah",
      "book_abbrev": "jer",
      "chapter": 6,
      "testament": "OT",
      "verses": [
        21
      ],
      "verse_count": 1
    },
    {
      "book": "Ezekiel",
      "book_abbrev": "ezk",
      "chapter": 3,
      "testament": "OT",
      "verses": [
        7,
        20
      ],
      "verse_count": 2
    },
    {
      "book": "Zephaniah",
      "book_abbrev": "zep",
      "chapter": 1,
      "testament": "OT",
      "verses": [
        3
      ],
      "verse_count": 1
    },
    {
      "book": "Luke",
      "book_abbrev": "luk",
      "chapter": 11,
      "testament": "NT",
      "verses": [
        52
      ],
      "verse_count": 1
    },
    {
      "book": "Romans",
      "book_abbrev": "rom",
      "chapter": 9,
      "testament": "NT",
      "verses": [
        1,
        32,
        33
      ],
      "verse_count": 3
    },
    {
      "book": "Romans",
      "book_abbrev": "rom",
      "chapter": 11,
      "testament": "NT",
      "verses": [
        9,
        14
      ],
      "verse_count": 2
    },
    {
      "book": "1 Corinthians",
      "book_abbrev": "1co",
      "chapter": 1,
      "testament": "NT",
      "verses": [
        8,
        23
      ],
      "verse_count": 2
    },
    {
      "book": "1 Peter",
      "book_abbrev": "1pe",
      "chapter": 1,
      "testament": "NT",
      "verses": [
        8
      ],
      "verse_count": 1
    },
    {
      "book": "Revelation",
      "book_abbrev": "rev",
      "chapter": 2,
      "testament": "NT",
      "verses": [
        14
      ],
      "verse_count": 1
    }
  ],
  "see_also": [
    "TEMPTATION"
  ],
  "aliases": [],
  "stats": {
    "entries_count": 1,
    "ot_refs": 5,
    "nt_refs": 6,
    "total_verses": 11
  },
  "definitions": [],
  "sources": [
    "NAV"
  ],
  "metadata": {
    "schema_version": "v3.0",
    "created_at": "2025-12-02T21:53:08.727831+00:00",
    "merged_from": {
      "v2": true,
      "dictionary": false
    }
  },
  "version": "3.0.0"
}