{
  "topic": "ZACHARIAS (ZECHARIAH)",
  "topic_slug": "zacharias__zechariah_",
  "canonical_id": "NAV:zacharias__zechariah_",
  "aliases": [],
  "see_also": [
    "JOHN THE BAPTIST",
    "ELISABETH"
  ],
  "see_also_resolved": [
    {
      "original": "JOHN THE BAPTIST",
      "clean": "JOHN THE BAPTIST",
      "slug": "john_the_baptist",
      "canonical_id": "NAV:john_the_baptist"
    },
    {
      "original": "ELISABETH",
      "clean": "ELISABETH",
      "slug": "elisabeth",
      "canonical_id": "NAV:elisabeth"
    }
  ],
  "raw_block": "–1. A man who was killed by the Jews\n  .Referred to by JesusMt 23:35;Lu 11:51\n–2. The father of John the BaptistLu 1:5-80;3:2\n  .SeeELISABETH\n  .SeeJOHN THE BAPTIST",
  "content_preview": "–1. A man who was killed by the Jews",
  "reference_groups": [
    {
      "idx": 0,
      "entry_label": "–1. A man who was killed by the Jews",
      "raw_segment": "–1. A man who was killed by the Jews"
    },
    {
      "idx": 1,
      "entry_label": "–2. The father of John the BaptistLu 1:5-80;3:2",
      "raw_segment": "–2. The father of John the BaptistLu 1:5-80;3:2"
    }
  ],
  "biblical_references": [],
  "books_mentioned": [],
  "normalized_labels": [],
  "stats": {
    "entries_count": 1,
    "ot_refs": 0,
    "nt_refs": 0,
    "total_verses": 0,
    "top_books": [],
    "ref_counts_by_book": {}
  },
  "source": {
    "provider": "ccel",
    "work": "Nave's Topical Bible",
    "format": "xml",
    "fetched_at": "2025-09-20",
    "source_url": null,
    "local_file": "data/datasets/ccel-paragraphs/ccel/n/nave/bible.xml"
  },
  "metadata": {
    "parser": "ccel-nave-xml-parser",
    "parser_version": "2025.09.19",
    "schema_version": "scrape.v1",
    "language": {
      "code": "en",
      "name": "English",
      "direction": "ltr"
    },
    "integrity": {
      "checksum_raw_block": "sha256:a61f82a89adbc05ea3458a7466532d6f604e06bfec9aab03b3caf180ff61e729",
      "position": {
        "start_line": null,
        "end_line": null,
        "total_lines": 5
      }
    },
    "notes": [
      "XML-based parsing from official CCEL ThML source",
      "Perfect biblical reference extraction with osisRef",
      "Structured hierarchy preservation",
      "Complete topic linking and see_also resolution"
    ]
  },
  "total_references": 0,
  "version": "1.0.0",
  "created_at": "2025-09-20T17:32:44.657380Z",
  "updated_at": "2025-09-20T17:32:44.657388Z"
}